{
  "result": {
    "item": "industrialforegoing:animal_byproduct_recolector"
  },
  "pattern": [
    "pep",
    "bmb",
    "brb"
  ],
  "conditions": [
    {
      "type": "forge:and",
      "values": [
        {
          "type": "forge:mod_loaded",
          "modid": "enderio"
        },
        {
          "type": "industrialforegoing:configuration_value",
          "value": "useEnderIOFrames"
        }
      ]
    }
  ],
  "type": "minecraft:crafting_shaped",
  "key": {
    "p": {
      "item": "#ITEMRUBBER"
    },
    "b": {
      "item": "minecraft:brick"
    },
    "r": {
      "item": "minecraft:redstone"
    },
    "e": {
      "item": "minecraft:bucket"
    },
    "m": {
      "item": "enderio:item_material",
      "data": 0
    }
  }
}