{
  "result": {
    "item": "industrialforegoing:enchantment_extractor"
  },
  "pattern": [
    "pnp",
    "bmb",
    "dgd"
  ],
  "conditions": [
    {
      "type": "forge:and",
      "values": [
        {
          "type": "forge:mod_loaded",
          "modid": "thermalexpansion"
        },
        {
          "type": "industrialforegoing:configuration_value",
          "value": "useTEFrames"
        }
      ]
    }
  ],
  "type": "forge:ore_shaped",
  "key": {
    "p": {
      "item": "#ITEMRUBBER"
    },
    "b": {
      "item": "minecraft:book"
    },
    "d": {
      "item": "#GEMDIAMOND"
    },
    "g": {
      "item": "#GEARGOLD"
    },
    "m": {
      "item": "thermalexpansion:frame",
      "data": 0
    },
    "n": {
      "item": "#INGOTBRICKNETHER"
    }
  }
}