{
  "type": "forge:conditional",
  "recipes": [
    {
      "conditions": [
        {
          "type": "forge:and",
          "values": [
            {
              "type": "forge:item_exists",
              "item": "industrialforegoing:conveyor_insertion_upgrade"
            }
          ]
        }
      ],
      "recipe": {
        "type": "minecraft:crafting_shaped",
        "category": "misc",
        "key": {
          "C": {
            "item": "industrialforegoing:conveyor"
          },
          "D": {
            "item": "minecraft:hopper"
          },
          "I": {
            "tag": "forge:ingots/iron"
          },
          "P": {
            "tag": "forge:plastic"
          }
        },
        "pattern": [
          "IPI",
          "IDI",
          "ICI"
        ],
        "result": {
          "item": "industrialforegoing:conveyor_insertion_upgrade"
        },
        "show_notification": true
      }
    }
  ]
}