{
  "type": "forge:conditional",
  "recipes": [
    {
      "conditions": [
        {
          "values": [
            {
              "item": "industrialforegoing:mycelial_ender",
              "type": "forge:item_exists"
            }
          ],
          "type": "forge:and"
        }
      ],
      "recipe": {
        "type": "minecraft:crafting_shaped",
        "pattern": [
          "BBB",
          "BCB",
          "RMR"
        ],
        "key": {
          "R": {
            "item": "minecraft:redstone"
          },
          "B": {
            "item": "minecraft:ender_pearl"
          },
          "C": {
            "item": "minecraft:ender_eye"
          },
          "M": {
            "tag": "industrialforegoing:machine_frame/advanced"
          }
        },
        "result": {
          "item": "industrialforegoing:mycelial_ender"
        }
      }
    }
  ]
}