{
  "type": "forge:conditional",
  "recipes": [
    {
      "conditions": [
        {
          "type": "forge:and",
          "values": [
            {
              "type": "forge:item_exists",
              "item": "industrialforegoing:mycelial_slimey"
            }
          ]
        }
      ],
      "recipe": {
        "type": "minecraft:crafting_shaped",
        "category": "misc",
        "key": {
          "B": {
            "item": "minecraft:slime_block"
          },
          "C": {
            "item": "minecraft:milk_bucket"
          },
          "M": {
            "tag": "industrialforegoing:machine_frame/advanced"
          },
          "R": {
            "item": "minecraft:redstone"
          }
        },
        "pattern": [
          "BBB",
          "BCB",
          "RMR"
        ],
        "result": {
          "item": "industrialforegoing:mycelial_slimey"
        },
        "show_notification": true
      }
    }
  ]
}