{
  "type": "forge:conditional",
  "recipes": [
    {
      "conditions": [
        {
          "type": "forge:and",
          "values": [
            {
              "type": "forge:item_exists",
              "item": "industrialforegoing:plant_sower"
            }
          ]
        }
      ],
      "recipe": {
        "type": "minecraft:crafting_shaped",
        "category": "misc",
        "key": {
          "B": {
            "item": "minecraft:flower_pot"
          },
          "G": {
            "tag": "forge:gears/iron"
          },
          "L": {
            "item": "minecraft:piston"
          },
          "M": {
            "tag": "industrialforegoing:machine_frame/pity"
          },
          "P": {
            "tag": "forge:plastic"
          },
          "R": {
            "item": "minecraft:redstone"
          }
        },
        "pattern": [
          "PBP",
          "LML",
          "GRG"
        ],
        "result": {
          "item": "industrialforegoing:plant_sower"
        },
        "show_notification": true
      }
    }
  ]
}